{
	"info": {
		"_postman_id": "96fc9874-db4d-4d5b-bf29-99b46719daff",
		"name": "WITChallenge",
		"schema": "https://schema.getpostman.com/json/collection/v2.1.0/collection.json",
		"_exporter_id": "43758933"
	},
	"item": [
		{
			"name": "SUM",
			"request": {
				"method": "GET",
				"header": [],
				"url": {
					"raw": "http://localhost:8080/api/calculation/sum?a=1&b=2",
					"protocol": "http",
					"host": [
						"localhost"
					],
					"port": "8080",
					"path": [
						"api",
						"calculation",
						"sum"
					],
					"query": [
						{
							"key": "a",
							"value": "1"
						},
						{
							"key": "b",
							"value": "2"
						}
					]
				}
			},
			"response": []
		},
		{
			"name": "SUBTRACT",
			"request": {
				"method": "GET",
				"header": [],
				"url": {
					"raw": "http://localhost:8080/api/calculation/subtract?a=1&b=2",
					"protocol": "http",
					"host": [
						"localhost"
					],
					"port": "8080",
					"path": [
						"api",
						"calculation",
						"subtract"
					],
					"query": [
						{
							"key": "a",
							"value": "1"
						},
						{
							"key": "b",
							"value": "2"
						}
					]
				}
			},
			"response": []
		},
		{
			"name": "MULTIPLY",
			"request": {
				"method": "GET",
				"header": [],
				"url": {
					"raw": "http://localhost:8080/api/calculation/multiply?a=1&b=2",
					"protocol": "http",
					"host": [
						"localhost"
					],
					"port": "8080",
					"path": [
						"api",
						"calculation",
						"multiply"
					],
					"query": [
						{
							"key": "a",
							"value": "1"
						},
						{
							"key": "b",
							"value": "2"
						}
					]
				}
			},
			"response": []
		},
		{
			"name": "DIVIDE",
			"request": {
				"method": "GET",
				"header": [],
				"url": {
					"raw": "http://localhost:8080/api/calculation/divide?a=1&b=2",
					"protocol": "http",
					"host": [
						"localhost"
					],
					"port": "8080",
					"path": [
						"api",
						"calculation",
						"divide"
					],
					"query": [
						{
							"key": "a",
							"value": "1"
						},
						{
							"key": "b",
							"value": "2"
						}
					]
				}
			},
			"response": []
		}
	]
}